advanced_aicode-2.1.2.dist-info/licenses/LICENSE
aicode/__init__.py
aicode/__main__.py
aicode/aider_control.py
aicode/aider_update_result.py
aicode/args.py
aicode/background.py
aicode/build_cmd_list.py
aicode/cli.py
aicode/cli_test.py
aicode/config.py
aicode/models.py
aicode/openaicfg.py
aicode/paths.py
aicode/run_process.py
aicode/util.py
aicode/assets/example.txt
advanced_aicode-2.1.2.dist-info/METADATA
advanced_aicode-2.1.2.dist-info/WHEEL
advanced_aicode-2.1.2.dist-info/entry_points.txt
advanced_aicode-2.1.2.dist-info/top_level.txt
advanced_aicode-2.1.2.dist-info/RECORD
