Metadata-Version: 2.4
Name: advanced-aicode
Version: 2.1.2
Summary: Front End for Aider.chat which makes it super simple to use
Home-page: https://github.com/zackees/aicode
Maintainer: Zachary Vorhies
License: BSD 3-Clause License
Keywords: template-python-cmd
Classifier: Programming Language :: Python :: 3
Requires-Python: >=3.10
License-File: LICENSE
Requires-Dist: appdirs
Requires-Dist: setuptools
Requires-Dist: ruff
Requires-Dist: semi-secret>=1.0.4
Requires-Dist: uv-iso-env>=1.0.41
Requires-Dist: dotenv>=0.9.9
Provides-Extra: dev
Requires-Dist: black; extra == "dev"
Requires-Dist: isort; extra == "dev"
Requires-Dist: flake8; extra == "dev"
Requires-Dist: mypy; extra == "dev"
Requires-Dist: pylint; extra == "dev"
Requires-Dist: pytest; extra == "dev"
Requires-Dist: tox; extra == "dev"
Requires-Dist: ruff; extra == "dev"
Requires-Dist: pytest-xdist; extra == "dev"
Dynamic: home-page
Dynamic: license-file
Dynamic: maintainer
